pyeph/.files/EPH_tot_urbano_estructura_bases.xlsx
pyeph/__init__.py
pyeph/ads.py
pyeph/calc/__init__.py
pyeph/calc/_base_calculator.py
pyeph/calc/_template.py
pyeph/calc/_types.py
pyeph/calc/dwelling.py
pyeph/calc/labor_market.py
pyeph/calc/poverty.py
pyeph/config.py
pyeph/errors.py
pyeph/get/__init__.py
pyeph/get/_base_getter.py
pyeph/get/basket.py
pyeph/get/equivalent_adult.py
pyeph/get/mautic.py
pyeph/get/microdata.py
pyeph/tools/.examples/canasta_ejemplo.csv
pyeph/tools/__init__.py
pyeph/tools/decorators.py
pyeph/tools/labels.py
pyeph/tools/merge.py
pyeph-1.6.1.dist-info/METADATA
pyeph-1.6.1.dist-info/WHEEL
pyeph-1.6.1.dist-info/licenses/LICENCE
pyeph-1.6.1.dist-info/RECORD
