Metadata-Version: 2.4
Name: pyeph
Version: 1.6.1
Summary: PyEPH es una librería para el procesamiento de la Encuesta Permanente de Hogares (eph) en Python. Permite la descarga de archivos de EPH's y otros como la canasta basica y adulto equivalente , como asi también algunos calculos rápidos relacionados con las mismas
License: MIT
License-File: LICENCE
Author: Maria Carolina Trogliero, Mariano Valdez Anopa, Maria Gaska
Requires-Python: >=3.10,<4.0
Classifier: License :: OSI Approved :: MIT License
Classifier: Programming Language :: Python :: 3
Classifier: Programming Language :: Python :: 3.10
Classifier: Programming Language :: Python :: 3.11
Classifier: Programming Language :: Python :: 3.12
Classifier: Programming Language :: Python :: 3.13
Classifier: Programming Language :: Python :: 3.14
Requires-Dist: ipykernel (>=6.13.0,<7.0.0)
Requires-Dist: openpyxl (>=3.0.10,<4.0.0)
Requires-Dist: pandas (>=2.0.0,<3.0.0)
Requires-Dist: requests (>=2.31.0,<3.0.0)
Requires-Dist: tqdm (>=4.66.0,<5.0.0)
Requires-Dist: xlrd (>=2.0.1,<3.0.0)
Project-URL: Documentation, https://pyeph.readthedocs.io/es/latest/
Project-URL: Homepage, https://github.com/institutohumai/pyeph/
